pyexpertsender-0.3.3.dist-info/RECORD
pyexpertsender-0.3.3.dist-info/metadata.json
pyexpertsender-0.3.3.dist-info/WHEEL
pyexpertsender-0.3.3.dist-info/DESCRIPTION.rst
pyexpertsender-0.3.3.dist-info/top_level.txt
pyexpertsender-0.3.3.dist-info/METADATA
pyexpertsender/__init__.py
pyexpertsender/utils.py
pyexpertsender/pyexpertsender.py
