Metadata-Version: 2.0
Name: pyexpertsender
Version: 0.3.3
Summary: Python wrapper for ExpertSender
Home-page: https://github.com/zlebnik/pyexpertsender
Author: Gleb Kovalev
Author-email: gleb@popmechanic.ru
License: MIT
Keywords: api wrapper ExpertSender
Platform: UNKNOWN
Classifier: Development Status :: 4 - Beta
Classifier: Intended Audience :: Developers
Classifier: License :: OSI Approved :: MIT License
Classifier: Programming Language :: Python :: 2
Classifier: Programming Language :: Python :: 2.6
Classifier: Programming Language :: Python :: 2.7
Classifier: Programming Language :: Python :: 3.6
Requires-Dist: furl
Requires-Dist: requests
Requires-Dist: xmltodict
Requires-Dist: six
